nicola_student_tracker/.config
nicola_student_tracker/README.md
nicola_student_tracker/__init__.py
nicola_student_tracker/app.py
nicola_student_tracker/assets/static/images/overview.png
nicola_student_tracker/assets/static/images/subjects.png
nicola_student_tracker/assets/static/images/table_stats.png
nicola_student_tracker/assets/static/images/xlsx_example.png
nicola_student_tracker/assets/style.css
nicola_student_tracker/command_line/cli.py
nicola_student_tracker/config.py
nicola_student_tracker/data/attendance.xlsx
nicola_student_tracker/pages/about.py
nicola_student_tracker/pages/components/card.py
nicola_student_tracker/pages/components/navbar.py
nicola_student_tracker/pages/components/table.py
nicola_student_tracker/pages/overview.py
nicola_student_tracker/pages/subjects.py
nicola_student_tracker/resources/dash_logic.py
nicola_student_tracker/resources/dataframe.py
nicola_student_tracker-0.0.2.dist-info/METADATA
nicola_student_tracker-0.0.2.dist-info/WHEEL
nicola_student_tracker-0.0.2.dist-info/entry_points.txt
nicola_student_tracker-0.0.2.dist-info/RECORD
