Metadata-Version: 2.1
Name: nicola-student-tracker
Version: 0.0.2
Summary: Simple package to display student progress.
License: MIT
Author: michael
Author-email: michael__brown@tutanota.com
Requires-Python: >=3.10,<4.0
Classifier: License :: OSI Approved :: MIT License
Classifier: Programming Language :: Python :: 3
Classifier: Programming Language :: Python :: 3.10
Classifier: Programming Language :: Python :: 3.11
Requires-Dist: black (>=23.9.1,<24.0.0)
Requires-Dist: dash (>=2.13.0,<3.0.0)
Requires-Dist: dash-bootstrap-components (>=1.5.0,<2.0.0)
Requires-Dist: openpyxl (>=3.1.2,<4.0.0)
Requires-Dist: pandas (>=2.1.0,<3.0.0)
Requires-Dist: pydantic-settings (>=2.0.3,<3.0.0)
Requires-Dist: pytest (>=7.4.2,<8.0.0)
Requires-Dist: pytest-cov (>=4.1.0,<5.0.0)
